{
  "title": "Basic Area",
  "externals": [
    "https://apexcharts.com/samples/assets/stock-prices.js"
  ],
  "files": [
    {
      "name": "chart.js",
      "language": "javascript",
      "code": "var options = {\n  series: [\n    {\n      name: 'Share Price',\n      data: series.monthDataSeries1.prices,\n    },\n  ],\n  chart: {\n    type: 'area',\n    height: 350,\n    zoom: {\n      enabled: false,\n    },\n  },\n  dataLabels: {\n    enabled: false,\n  },\n  stroke: {\n    curve: 'straight',\n  },\n\n  title: {\n    text: 'Meridian Corp Share Price',\n    align: 'left',\n  },\n  subtitle: {\n    text: 'Daily close, last quarter',\n    align: 'left',\n  },\n  labels: series.monthDataSeries1.dates.map(function (d) {\n    return d.replace('2017', '2025')\n  }),\n  xaxis: {\n    type: 'datetime',\n  },\n  legend: {\n    horizontalAlign: 'left',\n  },\n}\n\nvar chart = new ApexCharts(document.querySelector('#chart'), options)\nchart.render()\n"
    },
    {
      "name": "index.html",
      "language": "xml",
      "code": "<!DOCTYPE html>\n<html>\n  <head>\n    <title>Basic Area</title>\n    <link href=\"styles.css\" rel=\"stylesheet\" />\n    <script src=\"https://apexcharts.com/samples/assets/stock-prices.js\"></script>\n    <script src=\"https://cdn.jsdelivr.net/npm/apexcharts\"></script>\n  </head>\n  <body>\n    <div id=\"chart\"></div>\n\n    <script src=\"chart.js\"></script>\n  </body>\n</html>\n"
    },
    {
      "name": "styles.css",
      "language": "css",
      "code": "#chart {\n  max-width: 650px;\n  margin: 35px auto;\n}\n"
    }
  ]
}