{
  "title": "Context Menu: Right-Click Actions (chart.contextMenu)",
  "externals": [],
  "files": [
    {
      "name": "App.jsx",
      "language": "javascript",
      "code": "import React from 'react'\nimport ReactApexChart from 'react-apexcharts'\nimport ApexCharts from 'apexcharts'\nimport './styles.css'\n\nfunction series() {\n  var out = []\n  var v = 2200\n  for (var i = 0; i < 60; i++) {\n    v += Math.sin(i / 4) * 55 + i * 5 - 6\n    out.push([i, Math.round(v)])\n  }\n  return out\n}\n\nconst ApexChart = () => {\n  const [state, setState] = React.useState({\n    series: [{ name: 'Revenue', data: series() }],\n    options: {\n      chart: {\n        id: 'ctxmenu',\n        type: 'line',\n        height: 400,\n        fontFamily: 'Helvetica, Arial, sans-serif',\n        animations: { enabled: false },\n        toolbar: { show: false },\n        zoom: { enabled: true, type: 'x' },\n        contextMenu: {\n          enabled: true,\n          line: { text: 'Event', strokeDashArray: 5, color: '#7c3aed' },\n          items: [\n            'annotate',\n            'xline',\n            'yline',\n            'measure',\n            {\n              id: 'copyValue',\n              label: 'Copy value',\n              onClick: function (chart, ctx) {\n                var msg = 'x=' + Math.round(ctx.x) + ', y=' + Math.round(ctx.y)\n                var readout = document.getElementById('cm-readout')\n                if (readout) readout.textContent = 'Copied ' + msg\n                if (navigator.clipboard)\n                  navigator.clipboard.writeText(msg).catch(function () {})\n              },\n            },\n          ],\n        },\n        measure: { enabled: true },\n        ink: { enabled: true },\n      },\n      stroke: { width: 2, curve: 'smooth' },\n      colors: ['#2563eb'],\n      dataLabels: { enabled: false },\n      title: {\n        text: 'Revenue (right-click to add notes or measure)',\n        align: 'left',\n      },\n      xaxis: { type: 'numeric', title: { text: 'Session' } },\n      yaxis: { title: { text: 'Revenue' }, decimalsInFloat: 0 },\n    },\n  })\n\n  React.useEffect(() => {\n    // The react-apexcharts wrapper owns the render, so reach the live instance by\n    // its chart.id, then wire the same readout events the vanilla build does.\n    // (The context menu, ink and measure config all live in the chart options.)\n    let chart\n    const timer = window.setInterval(() => {\n      chart = ApexCharts.getChartByID('ctxmenu')\n      if (!chart) return\n      window.clearInterval(timer)\n\n      const readout = document.getElementById('cm-readout')\n      chart.addEventListener('measured', (c, o) => {\n        readout.textContent =\n          'Measured: dy=' +\n          Number(o.dy).toFixed(0) +\n          ' (' +\n          (o.percentChange >= 0 ? '+' : '') +\n          Number(o.percentChange).toFixed(1) +\n          '%)'\n      })\n      chart.addEventListener('annotationCreated', (c, o) => {\n        const kind =\n          o && o.type === 'xaxis'\n            ? 'Dashed line'\n            : o && o.type === 'yaxis'\n              ? 'Level line'\n              : 'Note'\n        readout.textContent =\n          kind +\n          ' added. Type to rename it; the floating card restyles or deletes it. Drag to move.'\n      })\n    }, 50)\n\n    return () => window.clearInterval(timer)\n  }, [])\n\n  return (\n    <div>\n      <div className=\"cm-panel\">\n        <div className=\"cm-readout\" id=\"cm-readout\">\n          Right-click anywhere on the plot to open the actions menu.\n        </div>\n      </div>\n\n      <div id=\"chart\">\n        <ReactApexChart\n          options={state.options}\n          series={state.series}\n          type=\"line\"\n          height={400}\n        />\n      </div>\n\n      <div className=\"cm-panel\">\n        <div className=\"cm-note\">\n          Right-click (or long-press) the plot to open an anchored actions menu.\n          Because each verb receives the clicked data point, it acts{' '}\n          <b>right there</b>, not chart-wide like a toolbar button:{' '}\n          <b>Add note here</b> drops an editable, draggable callout at the click\n          and opens its floating editor (type to rename; the card also offers\n          accent colors, bold, text size, marker size/shape and delete, via{' '}\n          <code>chart.ink</code>). <b>Annotate here</b>\n          drops a dashed vertical line at the clicked x, and{' '}\n          <b>Mark this level</b>a dashed horizontal line at the clicked y:\n          always a line, never a rectangle, styled via{' '}\n          <code>contextMenu.line</code> (label text, dash pattern, color) and\n          just as draggable, restylable and undoable as the note. A line's\n          editor card has separate <b>Label</b> and <b>Line</b> color rows, so a\n          white label chip never blanks the stroke. Click any note or line later\n          to reopen its editor.\n          <b>Measure from here</b> seeds the ruler at the click, then a second\n          click completes the measurement (<code>chart.measure</code>). The{' '}\n          <b>Copy value</b> entry below is a custom item wired via\n          <code>contextMenu.items[].onClick</code>. Arrow keys move, Enter\n          activates, Escape closes.\n        </div>\n      </div>\n    </div>\n  )\n}\n\nexport default ApexChart\n"
    },
    {
      "name": "styles.css",
      "language": "css",
      "code": "#chart {\n  max-width: 820px;\n  margin: 12px auto;\n}\n.cm-panel {\n  max-width: 820px;\n  margin: 12px auto;\n  font-family: Helvetica, Arial, sans-serif;\n}\n.cm-note {\n  background: #eef6ff;\n  border-left: 3px solid #2563eb;\n  padding: 11px 15px;\n  font-size: 13px;\n  color: #234;\n  border-radius: 2px;\n  line-height: 1.6;\n  margin: 12px 6px;\n}\n.cm-note code {\n  background: #dbeafe;\n  padding: 1px 5px;\n  border-radius: 3px;\n}\n.cm-readout {\n  font-family: monospace;\n  font-size: 13px;\n  color: #445;\n  margin: 6px 6px 0;\n}\n"
    }
  ]
}