{
  "title": "Ink Layer: Drag Annotations Directly (chart.ink)",
  "externals": [],
  "files": [
    {
      "name": "App.vue",
      "language": "xml",
      "code": "<template>\n  <div>\n    <div class=\"ink-wrap\">\n      <div class=\"ink-bar\">\n        <span class=\"readout\" id=\"ink-readout\"\n          >Drag a labelled point to reposition it</span\n        >\n      </div>\n\n      <div id=\"chart\">\n        <apexchart\n          type=\"line\"\n          height=\"380\"\n          :options=\"chartOptions\"\n          :series=\"series\"\n        ></apexchart>\n      </div>\n\n      <div class=\"ink-note\">\n        The chart sets <code>chart.ink.enabled</code>, so its point annotations\n        are <b>draggable</b>: grab a labelled marker and move it.\n        <b>Click a note</b> to open its floating editor card: rename it inline,\n        pick an accent color, toggle bold, step the text size, grow/shrink or\n        reshape the <b>marker</b>, or <b>delete</b> the note (Enter commits,\n        Escape closes; the swatches come from\n        <code>chart.ink.noteColors</code>). On release of a drag the new\n        position is converted back to data coordinates and written to\n        <code>annotations.points[].x/y</code>, so the annotation stays glued to\n        that data location on later zoom or resize. Use <b>+ Note</b> (the\n        palette, from <code>chart.ink.palette</code>) then click the plot to\n        drop a new labelled note. The x-axis <b>Window</b> band moves (drag its\n        middle) or resizes (drag an edge), and the y-axis <b>Target</b> line\n        drags vertically. Fires <code>annotationDragged</code> /\n        <code>annotationEdited</code> / <code>annotationStyled</code> /\n        <code>annotationCreated</code> / <code>annotationDeleted</code>. With\n        the history (Rewind) feature enabled, <b>Ctrl/Cmd+Z</b> undoes any edit\n        and Shift+Ctrl/Cmd+Z redoes it. Needs the <code>ink</code> feature. (Set\n        <code>draggable:false</code> on a single annotation to pin it.)\n      </div>\n    </div>\n  </div>\n</template>\n\n<script>\nimport VueApexCharts from 'vue-apexcharts'\nimport ApexCharts from 'apexcharts'\n\nfunction signal() {\n  var out = []\n  for (var i = 0; i < 40; i++) {\n    var v = 50 + 22 * Math.sin(i / 4.0) + 9 * Math.sin(i / 1.4) + i * 0.4\n    out.push([i, Math.round(v)])\n  }\n  return out\n}\n\nexport default {\ncomponents: {\napexchart: VueApexCharts,\n},\ndata: function () {\nreturn {\nseries: [\n  { name: 'Signal', data: signal() }\n],\nchartOptions: {\nchart: {\n  id: 'signal',\n  type: 'line',\n  height: 380,\n  fontFamily: 'Helvetica, Arial, sans-serif',\n  animations: { enabled: false },\n  ink: { enabled: true, palette: true },\n  history: { enabled: true },\n  toolbar: { show: false },\n  zoom: { enabled: false },\n},\nstroke: { width: 2, curve: 'smooth' },\ncolors: ['#6366f1'],\ntitle: { text: 'Signal (drag the callouts)', align: 'left' },\nxaxis: { type: 'numeric', title: { text: 'Sample' } },\nyaxis: { title: { text: 'Value' } },\nannotations: {\n  points: [\n    {\n      x: 6, y: 74, id: 'peak',\n      marker: { size: 7, fillColor: '#fff', strokeColor: '#6366f1', strokeWidth: 3 },\n      label: { text: 'Peak', borderColor: '#6366f1', style: { color: '#fff', background: '#6366f1' } },\n    },\n    {\n      x: 20, y: 52, id: 'dip',\n      marker: { size: 7, fillColor: '#fff', strokeColor: '#ef4444', strokeWidth: 3 },\n      label: { text: 'Watch', borderColor: '#ef4444', style: { color: '#fff', background: '#ef4444' } },\n    },\n  ],\n  xaxis: [\n    {\n      x: 10, x2: 16, id: 'window', fillColor: '#a5b4fc', opacity: 0.28,\n      label: { text: 'Window', style: { color: '#fff', background: '#6366f1' } },\n    },\n  ],\n  yaxis: [\n    {\n      y: 62, id: 'target', borderColor: '#f59e0b', strokeDashArray: 4,\n      label: { text: 'Target', style: { color: '#fff', background: '#f59e0b' } },\n    },\n  ],\n},\n},\n}\n},\nmounted: function () {\n  // The vue-apexcharts wrapper owns the render, so reach the live instance by\n  // its chart.id. Poll until it exists, then wire the same readout the vanilla\n  // build does. The ink feature drives the chart instance directly (drag / edit\n  // annotations), so no reactive data changes and the chart is not re-rendered.\n  var timer = window.setInterval(function () {\n    var chart = ApexCharts.getChartByID('signal')\n    if (!chart) return\n    window.clearInterval(timer)\n\n    var readout = document.getElementById('ink-readout')\n\n    chart.addEventListener('annotationDragged', function (c, o) {\n      readout.textContent =\n        \"Moved '\" + o.id + \"' to x=\" + Number(o.x).toFixed(2) + ', y=' + Number(o.y).toFixed(2)\n    })\n    chart.addEventListener('annotationStyled', function (c, o) {\n      readout.textContent = \"Restyled '\" + o.id + \"'\"\n    })\n    chart.addEventListener('annotationDeleted', function (c, o) {\n      readout.textContent = \"Deleted '\" + o.id + \"' (Ctrl/Cmd+Z restores it)\"\n    })\n  }, 50)\n},,\n}\n</script>\n\n<style>\n.ink-wrap {\n  max-width: 820px;\n  margin: 12px auto;\n  font-family: Helvetica, Arial, sans-serif;\n}\n.ink-bar {\n  display: flex;\n  gap: 12px;\n  align-items: center;\n  flex-wrap: wrap;\n  margin: 4px 6px 10px;\n}\n.ink-bar .readout {\n  font-family: monospace;\n  font-size: 13px;\n  color: #445;\n}\n.ink-note {\n  background: #eef2ff;\n  border-left: 3px solid #6366f1;\n  padding: 11px 15px;\n  font-size: 13px;\n  color: #234;\n  border-radius: 2px;\n  line-height: 1.6;\n  margin: 12px 6px;\n}\n.ink-note code {\n  background: #dfe3ff;\n  padding: 1px 5px;\n  border-radius: 3px;\n}\n</style>\n"
    }
  ]
}